payne/__init__.py
payne/app.py
payne/app_metadata.py
payne/cli.py
payne/payne.py
payne/pyproject.py
payne/uv.py
payne-0.1.0.dist-info/METADATA
payne-0.1.0.dist-info/WHEEL
payne-0.1.0.dist-info/entry_points.txt
payne-0.1.0.dist-info/licenses/LICENSE
payne-0.1.0.dist-info/RECORD
