Metadata-Version: 2.4
Name: payne
Version: 0.1.0
Summary: Install Python applications
Author-email: Martin Herrmann <martin@famherrmann.de>
License-File: LICENSE
Requires-Python: >=3.11
Requires-Dist: cyclopts>=3.3.1
